modules/acm/acm_fpga/rtl/sine_lut.v
// generated: 256-entry, one-period, 12-bit unsigned sine ROM (centered 2048)
module sine_lut (input wire [7:0] addr, output reg [11:0] data);
  always @(*) begin
    case (addr)
      8'd0  : data = 12'd2048;
      8'd1  : data = 12'd2098;
      8'd2  : data = 12'd2148;
      8'd3  : data = 12'd2199;
      8'd4  : data = 12'd2249;
      8'd5  : data = 12'd2299;
      8'd6  : data = 12'd2348;
      8'd7  : data = 12'd2398;
      8'd8  : data = 12'd2447;
      8'd9  : data = 12'd2497;
      8'd10 : data = 12'd2545;
      8'd11 : data = 12'd2594;
      8'd12 : data = 12'd2642;
      8'd13 : data = 12'd2690;
      8'd14 : data = 12'd2738;
      8'd15 : data = 12'd2785;
      8'd16 : data = 12'd2831;
      8'd17 : data = 12'd2878;
      8'd18 : data = 12'd2923;
      8'd19 : data = 12'd2968;
      8'd20 : data = 12'd3013;
      8'd21 : data = 12'd3057;
      8'd22 : data = 12'd3100;
      8'd23 : data = 12'd3143;
      8'd24 : data = 12'd3185;
      8'd25 : data = 12'd3227;
      8'd26 : data = 12'd3267;
      8'd27 : data = 12'd3307;
      8'd28 : data = 12'd3347;
      8'd29 : data = 12'd3385;
      8'd30 : data = 12'd3423;
      8'd31 : data = 12'd3459;
      8'd32 : data = 12'd3495;
      8'd33 : data = 12'd3531;
      8'd34 : data = 12'd3565;
      8'd35 : data = 12'd3598;
      8'd36 : data = 12'd3630;
      8'd37 : data = 12'd3662;
      8'd38 : data = 12'd3692;
      8'd39 : data = 12'd3722;
      8'd40 : data = 12'd3750;
      8'd41 : data = 12'd3777;
      8'd42 : data = 12'd3804;
      8'd43 : data = 12'd3829;
      8'd44 : data = 12'd3853;
      8'd45 : data = 12'd3876;
      8'd46 : data = 12'd3898;
      8'd47 : data = 12'd3919;
      8'd48 : data = 12'd3939;
      8'd49 : data = 12'd3958;
      8'd50 : data = 12'd3975;
      8'd51 : data = 12'd3992;
      8'd52 : data = 12'd4007;
      8'd53 : data = 12'd4021;
      8'd54 : data = 12'd4034;
      8'd55 : data = 12'd4045;
      8'd56 : data = 12'd4056;
      8'd57 : data = 12'd4065;
      8'd58 : data = 12'd4073;
      8'd59 : data = 12'd4080;
      8'd60 : data = 12'd4085;
      8'd61 : data = 12'd4089;
      8'd62 : data = 12'd4093;
      8'd63 : data = 12'd4094;
      8'd64 : data = 12'd4095;
      8'd65 : data = 12'd4094;
      8'd66 : data = 12'd4093;
      8'd67 : data = 12'd4089;
      8'd68 : data = 12'd4085;
      8'd69 : data = 12'd4080;
      8'd70 : data = 12'd4073;
      8'd71 : data = 12'd4065;
      8'd72 : data = 12'd4056;
      8'd73 : data = 12'd4045;
      8'd74 : data = 12'd4034;
      8'd75 : data = 12'd4021;
      8'd76 : data = 12'd4007;
      8'd77 : data = 12'd3992;
      8'd78 : data = 12'd3975;
      8'd79 : data = 12'd3958;
      8'd80 : data = 12'd3939;
      8'd81 : data = 12'd3919;
      8'd82 : data = 12'd3898;
      8'd83 : data = 12'd3876;
      8'd84 : data = 12'd3853;
      8'd85 : data = 12'd3829;
      8'd86 : data = 12'd3804;
      8'd87 : data = 12'd3777;
      8'd88 : data = 12'd3750;
      8'd89 : data = 12'd3722;
      8'd90 : data = 12'd3692;
      8'd91 : data = 12'd3662;
      8'd92 : data = 12'd3630;
      8'd93 : data = 12'd3598;
      8'd94 : data = 12'd3565;
      8'd95 : data = 12'd3531;
      8'd96 : data = 12'd3495;
      8'd97 : data = 12'd3459;
      8'd98 : data = 12'd3423;
      8'd99 : data = 12'd3385;
      8'd100: data = 12'd3347;
      8'd101: data = 12'd3307;
      8'd102: data = 12'd3267;
      8'd103: data = 12'd3227;
      8'd104: data = 12'd3185;
      8'd105: data = 12'd3143;
      8'd106: data = 12'd3100;
      8'd107: data = 12'd3057;
      8'd108: data = 12'd3013;
      8'd109: data = 12'd2968;
      8'd110: data = 12'd2923;
      8'd111: data = 12'd2878;
      8'd112: data = 12'd2831;
      8'd113: data = 12'd2785;
      8'd114: data = 12'd2738;
      8'd115: data = 12'd2690;
      8'd116: data = 12'd2642;
      8'd117: data = 12'd2594;
      8'd118: data = 12'd2545;
      8'd119: data = 12'd2497;
      8'd120: data = 12'd2447;
      8'd121: data = 12'd2398;
      8'd122: data = 12'd2348;
      8'd123: data = 12'd2299;
      8'd124: data = 12'd2249;
      8'd125: data = 12'd2199;
      8'd126: data = 12'd2148;
      8'd127: data = 12'd2098;
      8'd128: data = 12'd2048;
      8'd129: data = 12'd1998;
      8'd130: data = 12'd1948;
      8'd131: data = 12'd1897;
      8'd132: data = 12'd1847;
      8'd133: data = 12'd1797;
      8'd134: data = 12'd1748;
      8'd135: data = 12'd1698;
      8'd136: data = 12'd1649;
      8'd137: data = 12'd1599;
      8'd138: data = 12'd1551;
      8'd139: data = 12'd1502;
      8'd140: data = 12'd1454;
      8'd141: data = 12'd1406;
      8'd142: data = 12'd1358;
      8'd143: data = 12'd1311;
      8'd144: data = 12'd1265;
      8'd145: data = 12'd1218;
      8'd146: data = 12'd1173;
      8'd147: data = 12'd1128;
      8'd148: data = 12'd1083;
      8'd149: data = 12'd1039;
      8'd150: data = 12'd996;
      8'd151: data = 12'd953;
      8'd152: data = 12'd911;
      8'd153: data = 12'd869;
      8'd154: data = 12'd829;
      8'd155: data = 12'd789;
      8'd156: data = 12'd749;
      8'd157: data = 12'd711;
      8'd158: data = 12'd673;
      8'd159: data = 12'd637;
      8'd160: data = 12'd601;
      8'd161: data = 12'd565;
      8'd162: data = 12'd531;
      8'd163: data = 12'd498;
      8'd164: data = 12'd466;
      8'd165: data = 12'd434;
      8'd166: data = 12'd404;
      8'd167: data = 12'd374;
      8'd168: data = 12'd346;
      8'd169: data = 12'd319;
      8'd170: data = 12'd292;
      8'd171: data = 12'd267;
      8'd172: data = 12'd243;
      8'd173: data = 12'd220;
      8'd174: data = 12'd198;
      8'd175: data = 12'd177;
      8'd176: data = 12'd157;
      8'd177: data = 12'd138;
      8'd178: data = 12'd121;
      8'd179: data = 12'd104;
      8'd180: data = 12'd89;
      8'd181: data = 12'd75;
      8'd182: data = 12'd62;
      8'd183: data = 12'd51;
      8'd184: data = 12'd40;
      8'd185: data = 12'd31;
      8'd186: data = 12'd23;
      8'd187: data = 12'd16;
      8'd188: data = 12'd11;
      8'd189: data = 12'd7;
      8'd190: data = 12'd3;
      8'd191: data = 12'd2;
      8'd192: data = 12'd1;
      8'd193: data = 12'd2;
      8'd194: data = 12'd3;
      8'd195: data = 12'd7;
      8'd196: data = 12'd11;
      8'd197: data = 12'd16;
      8'd198: data = 12'd23;
      8'd199: data = 12'd31;
      8'd200: data = 12'd40;
      8'd201: data = 12'd51;
      8'd202: data = 12'd62;
      8'd203: data = 12'd75;
      8'd204: data = 12'd89;
      8'd205: data = 12'd104;
      8'd206: data = 12'd121;
      8'd207: data = 12'd138;
      8'd208: data = 12'd157;
      8'd209: data = 12'd177;
      8'd210: data = 12'd198;
      8'd211: data = 12'd220;
      8'd212: data = 12'd243;
      8'd213: data = 12'd267;
      8'd214: data = 12'd292;
      8'd215: data = 12'd319;
      8'd216: data = 12'd346;
      8'd217: data = 12'd374;
      8'd218: data = 12'd404;
      8'd219: data = 12'd434;
      8'd220: data = 12'd466;
      8'd221: data = 12'd498;
      8'd222: data = 12'd531;
      8'd223: data = 12'd565;
      8'd224: data = 12'd601;
      8'd225: data = 12'd637;
      8'd226: data = 12'd673;
      8'd227: data = 12'd711;
      8'd228: data = 12'd749;
      8'd229: data = 12'd789;
      8'd230: data = 12'd829;
      8'd231: data = 12'd869;
      8'd232: data = 12'd911;
      8'd233: data = 12'd953;
      8'd234: data = 12'd996;
      8'd235: data = 12'd1039;
      8'd236: data = 12'd1083;
      8'd237: data = 12'd1128;
      8'd238: data = 12'd1173;
      8'd239: data = 12'd1218;
      8'd240: data = 12'd1265;
      8'd241: data = 12'd1311;
      8'd242: data = 12'd1358;
      8'd243: data = 12'd1406;
      8'd244: data = 12'd1454;
      8'd245: data = 12'd1502;
      8'd246: data = 12'd1551;
      8'd247: data = 12'd1599;
      8'd248: data = 12'd1649;
      8'd249: data = 12'd1698;
      8'd250: data = 12'd1748;
      8'd251: data = 12'd1797;
      8'd252: data = 12'd1847;
      8'd253: data = 12'd1897;
      8'd254: data = 12'd1948;
      8'd255: data = 12'd1998;
      default: data = 12'd2048;
    endcase
  end
endmodule

modules/acm/acm_fpga/rtl/fmc_mux_slave.v
// multiplexed-mode FMC slave (async, 16-bit) for the STM32H7 FMC.
//
// the STM32 drives the LOW address on AD[15:0] during NADV, then the same wires
// carry data. this slave latches the address, serves combinational reads, and
// latches writes. 16-bit bus.
//
// register map (16-bit, word-addressed; STM32 byte offset = word index * 2):
//   word 0     (0x60000000): ID        RO  0xACE1
//   word 1     (0x60000002): SCRATCH   RW
//   word 2     (0x60000004): LED_CTRL  RW  low 5 bits -> LEDs
//   word 3     (0x60000006): WAVE_SEL  RW  [1:0] 0=sine 1=saw 2=square 3=triangle
//   0x100-1FF  (0x60000200): AUDIO     RO  sample(index, WAVE_SEL), 12-bit in low bits
//
// the AUDIO region is one period of the selected waveform (256 x 12-bit). the
// STM32 reads it into a DAC buffer; WAVE_SEL picks the timbre. this is the
// minimal "wavetable generator" slice - DDS pitch + mixing come later.
//
// NADV/NOE/NWE/NE1 are asynchronous to clk; brought across with 2-FF synchronizers.

module fmc_mux_slave (
  input  wire        clk,        // 27 MHz fpga clock
  input  wire        rst,        // active high

  inout  wire [15:0] AD,         // 16-bit multiplexed address/data
  input  wire        NADV,       // NL  (active low) - address latch
  input  wire        NOE,        //     (active low) - read strobe
  input  wire        NWE,        //     (active low) - write strobe
  input  wire        NE1,        //     (active low) - chip select
  output wire        NWAIT,      //     (active low) - wait (inactive for PoC)

  output reg  [15:0] led_ctrl
);

  localparam [15:0] ID_VALUE = 16'hACE1;

  // ---- synchronize the async control strobes ----
  reg [1:0] ne1_s, noe_s, nwe_s, nadv_s;
  always @(posedge clk) begin
    ne1_s  <= {ne1_s[0],  NE1};
    noe_s  <= {noe_s[0],  NOE};
    nwe_s  <= {nwe_s[0],  NWE};
    nadv_s <= {nadv_s[0], NADV};
  end
  wire ne1  = ne1_s[1];
  wire noe  = noe_s[1];
  wire nwe  = nwe_s[1];
  wire nadv = nadv_s[1];

  // ---- synchronize the AD inputs ----
  reg [15:0] ad_s0, ad_in;
  always @(posedge clk) begin
    ad_s0 <= AD;
    ad_in <= ad_s0;
  end

  // ---- latch the address while NADV is asserted ----
  reg [15:0] addr;
  always @(posedge clk or posedge rst) begin
    if (rst) begin
      addr <= 16'd0;
    end
    else if (!nadv) begin
      addr <= ad_in;
    end
  end

  // ---- registers + write commit on the NWE rising edge ----
  reg [15:0] scratch;
  reg [1:0]  wave_sel;
  reg [15:0] wdata;
  reg        nwe_d;
  always @(posedge clk or posedge rst) begin
    if (rst) begin
      scratch  <= 16'd0;
      led_ctrl <= 16'd0;
      wave_sel <= 2'd0;
      wdata    <= 16'd0;
      nwe_d    <= 1'b1;
    end
    else begin
      nwe_d <= nwe;
      if (!ne1 && !nwe) begin
        wdata <= ad_in;
      end
      if (!ne1 && nwe && !nwe_d) begin
        case (addr)
          16'd1: scratch  <= wdata;
          16'd2: led_ctrl <= wdata;
          16'd3: wave_sel <= wdata[1:0];
          default: ;
        endcase
      end
    end
  end

  // ---- waveform generator: one period of the selected wave, by index ----
  wire [11:0] sine_s;
  sine_lut u_sine (.addr(addr[7:0]), .data(sine_s));

  wire [6:0] tri_idx = addr[7] ? (7'd127 - addr[6:0]) : addr[6:0];
  reg  [11:0] wave_s;
  always @(*) begin
    case (wave_sel)
      2'd0:    wave_s = sine_s;                  // sine (LUT)
      2'd1:    wave_s = {addr[7:0], 4'b0};       // sawtooth  (0..4080)
      2'd2:    wave_s = addr[7] ? 12'd0 : 12'd4095;  // square
      2'd3:    wave_s = {tri_idx, 5'b0};         // triangle  (0..4064)
      default: wave_s = sine_s;
    endcase
  end

  // ---- combinational read mux ----
  reg [15:0] rdata;
  always @(*) begin
    if (addr[15:8] == 8'h01) begin
      rdata = {4'b0, wave_s};              // AUDIO region 0x100-0x1FF
    end
    else begin
      case (addr)
        16'd0:   rdata = ID_VALUE;
        16'd1:   rdata = scratch;
        16'd2:   rdata = led_ctrl;
        16'd3:   rdata = {14'b0, wave_sel};
        default: rdata = 16'h0000;
      endcase
    end
  end

  // ---- drive AD only during the read data phase ----
  wire drive_ad = (!ne1) && (!noe);
  assign AD = drive_ad ? rdata : 16'bz;

  assign NWAIT = 1'b1;

endmodule

modules/acm/acm_fpga/sim/fmc_mux_slave_tb.v
// testbench for fmc_mux_slave: mimics the STM32 FMC multiplexed async cycles
// and checks ID read, scratch write/read-back, and the LED_CTRL register.
//
// run (icarus verilog):
//   iverilog -o fmc_tb ../rtl/fmc_mux_slave.v fmc_mux_slave_tb.v && vvp fmc_tb
// view waveforms: gtkwave fmc_tb.vcd

`timescale 1ns/1ps

module fmc_mux_slave_tb;

  reg         clk = 1'b0;
  reg         rst;
  reg         NE1, NOE, NWE, NADV;
  wire        NWAIT;
  wire [15:0] led_ctrl;

  // bidirectional AD: the testbench (master) drives address + write data;
  // the DUT drives read data
  reg  [15:0] tb_ad_out;
  reg         tb_ad_oe;
  wire [15:0] AD = tb_ad_oe ? tb_ad_out : 16'bz;

  fmc_mux_slave dut (
    .clk(clk), .rst(rst),
    .AD(AD), .NADV(NADV), .NOE(NOE), .NWE(NWE), .NE1(NE1), .NWAIT(NWAIT),
    .led_ctrl(led_ctrl)
  );

  always #10 clk = ~clk;          // 50 MHz sim clock

  integer errors = 0;

  task wait_clocks(input integer n);
    begin
      repeat (n) @(posedge clk);
    end
  endtask

  // one multiplexed write cycle
  task fmc_write(input [15:0] a, input [15:0] d);
    begin
      @(negedge clk);
      NE1 = 1'b0;
      // address phase: drive the address, pulse NADV low
      NADV = 1'b0; tb_ad_out = a; tb_ad_oe = 1'b1;
      wait_clocks(6);
      NADV = 1'b1;                 // address latched
      wait_clocks(4);
      // data phase: master drives write data, pulse NWE low
      tb_ad_out = d;
      NWE = 1'b0;
      wait_clocks(6);
      NWE = 1'b1;                  // rising edge -> slave commits
      wait_clocks(4);
      tb_ad_oe = 1'b0;            // release the bus
      NE1 = 1'b1;
      wait_clocks(6);
    end
  endtask

  // one multiplexed read cycle, with self-check
  task fmc_read(input [15:0] a, input [15:0] expect_d);
    reg [15:0] got;
    begin
      @(negedge clk);
      NE1 = 1'b0;
      // address phase
      NADV = 1'b0; tb_ad_out = a; tb_ad_oe = 1'b1;
      wait_clocks(6);
      NADV = 1'b1;
      wait_clocks(2);
      tb_ad_oe = 1'b0;           // master releases bus for turnaround
      wait_clocks(4);
      // data phase: assert NOE, let the slave drive, then sample
      NOE = 1'b0;
      wait_clocks(8);
      got = AD;
      NOE = 1'b1;
      NE1 = 1'b1;
      wait_clocks(6);
      if (got === expect_d) begin
        $display("PASS  read word %0d = 0x%04x", a, got);
      end
      else begin
        $display("FAIL  read word %0d = 0x%04x (expected 0x%04x)", a, got, expect_d);
        errors = errors + 1;
      end
    end
  endtask

  initial begin
    $dumpfile("fmc_tb.vcd");
    $dumpvars(0, fmc_mux_slave_tb);

    // idle bus
    NE1 = 1'b1; NOE = 1'b1; NWE = 1'b1; NADV = 1'b1;
    tb_ad_oe = 1'b0; tb_ad_out = 16'd0;

    rst = 1'b1; wait_clocks(5);
    rst = 1'b0; wait_clocks(5);

    fmc_read (16'd0, 16'hACE1);   // ID handshake
    fmc_read (16'd1, 16'h0000);   // scratch starts at 0
    fmc_write(16'd1, 16'h1234);   // write scratch
    fmc_read (16'd1, 16'h1234);   // read it back
    fmc_write(16'd2, 16'h002A);   // write LED_CTRL
    fmc_read (16'd2, 16'h002A);   // read it back

    if (led_ctrl === 16'h002A) begin
      $display("PASS  led_ctrl output = 0x%04x", led_ctrl);
    end
    else begin
      $display("FAIL  led_ctrl output = 0x%04x (expected 0x002A)", led_ctrl);
      errors = errors + 1;
    end

    if (errors == 0) begin
      $display("--- ALL TESTS PASSED ---");
    end
    else begin
      $display("--- %0d FAILURE(S) ---", errors);
    end
    $finish;
  end

  // watchdog
  initial begin
    #200000;
    $display("FAIL  timeout");
    $finish;
  end

endmodule

modules/acm/acm_fpga/sim/fmc_tb.vcd
$date
	Sat Jun 27 12:48:22 2026
$end
$version
	Icarus Verilog
$end
$timescale
	1ps
$end
$scope module fmc_mux_slave_tb $end
$var wire 16 ! AD [15:0] $end
$var wire 1 " NWAIT $end
$var wire 16 # led_ctrl [15:0] $end
$var reg 1 $ NADV $end
$var reg 1 % NE1 $end
$var reg 1 & NOE $end
$var reg 1 ' NWE $end
$var reg 1 ( clk $end
$var reg 1 ) rst $end
$var reg 1 * tb_ad_oe $end
$var reg 16 + tb_ad_out [15:0] $end
$var integer 32 , errors [31:0] $end
$scope module dut $end
$var wire 16 - AD [15:0] $end
$var wire 1 $ NADV $end
$var wire 1 % NE1 $end
$var wire 1 & NOE $end
$var wire 1 " NWAIT $end
$var wire 1 ' NWE $end
$var wire 1 ( clk $end
$var wire 1 . drive_ad $end
$var wire 1 ) rst $end
$var wire 7 / tri_idx [6:0] $end
$var wire 12 0 sine_s [11:0] $end
$var wire 1 1 nwe $end
$var wire 1 2 noe $end
$var wire 1 3 ne1 $end
$var wire 1 4 nadv $end
$var parameter 16 5 ID_VALUE $end
$var reg 16 6 ad_in [15:0] $end
$var reg 16 7 ad_s0 [15:0] $end
$var reg 16 8 addr [15:0] $end
$var reg 16 9 led_ctrl [15:0] $end
$var reg 2 : nadv_s [1:0] $end
$var reg 2 ; ne1_s [1:0] $end
$var reg 2 < noe_s [1:0] $end
$var reg 1 = nwe_d $end
$var reg 2 > nwe_s [1:0] $end
$var reg 16 ? rdata [15:0] $end
$var reg 16 @ scratch [15:0] $end
$var reg 12 A wave_s [11:0] $end
$var reg 2 B wave_sel [1:0] $end
$var reg 16 C wdata [15:0] $end
$scope module u_sine $end
$var wire 8 D addr [7:0] $end
$var reg 12 E data [11:0] $end
$upscope $end
$upscope $end
$scope task fmc_read $end
$var reg 16 F a [15:0] $end
$var reg 16 G expect_d [15:0] $end
$var reg 16 H got [15:0] $end
$upscope $end
$scope task fmc_write $end
$var reg 16 I a [15:0] $end
$var reg 16 J d [15:0] $end
$upscope $end
$scope task wait_clocks $end
$var integer 32 K n [31:0] $end
$upscope $end
$upscope $end
$enddefinitions $end
$comment Show the parameter values. $end
$dumpall
b1010110011100001 5
$end
#0
$dumpvars
b101 K
bx J
bx I
bx H
bx G
bx F
b100000000000 E
b0 D
b0 C
b0 B
b100000000000 A
b0 @
b1010110011100001 ?
bx >
1=
bx <
bx ;
bx :
b0 9
b0 8
bx 7
bx 6
x4
x3
x2
x1
b100000000000 0
b0 /
x.
bx -
b0 ,
b0 +
0*
1)
0(
1'
1&
1%
1$
b0 #
1"
bx !
$end
#10000
bx1 :
bx1 >
bx1 <
bx1 ;
1(
#20000
0(
#30000
bz !
bz -
0.
14
11
12
13
b11 :
b11 >
b11 <
b11 ;
1(
#40000
0(
#50000
bz 7
1(
#60000
0(
#70000
bz 6
1(
#80000
0(
#90000
0)
1(
#100000
0(
#110000
1(
#120000
0(
#130000
1(
#140000
0(
#150000
1(
#160000
0(
#170000
1(
#180000
0(
#190000
b1010110011100001 G
b0 F
1(
#200000
b0 !
b0 -
b110 K
1*
0$
0%
0(
#210000
b10 :
b10 ;
b0 7
1(
#220000
0(
#230000
04
03
b0 6
b0 :
b0 ;
1(
#240000
0(
#250000
1(
#260000
0(
#270000
1(
#280000
0(
#290000
1(
#300000
0(
#310000
b10 K
1$
1(
#320000
0(
#330000
b1 :
1(
#340000
0(
#350000
14
b11 :
bz !
bz -
b100 K
0*
1(
#360000
0(
#370000
bz 7
1(
#380000
0(
#390000
bz 6
1(
#400000
0(
#410000
1(
#420000
0(
#430000
b1000 K
0&
1(
#440000
0(
#450000
b10 <
1(
#460000
0(
#470000
b1010110011100001 !
b1010110011100001 -
1.
02
b0 <
1(
#480000
0(
#490000
b1010110011100001 7
1(
#500000
0(
#510000
b1010110011100001 6
1(
#520000
0(
#530000
1(
#540000
0(
#550000
1(
#560000
0(
#570000
1(
#580000
0(
#590000
b110 K
1%
1&
b1010110011100001 H
1(
#600000
0(
#610000
b1 <
b1 ;
1(
#620000
0(
#630000
bz !
bz -
0.
12
13
b11 <
b11 ;
1(
#640000
0(
#650000
bz 7
1(
#660000
0(
#670000
bz 6
1(
#680000
0(
#690000
1(
#700000
0(
#710000
b0 G
b1 F
1(
#720000
b1 !
b1 -
1*
b1 +
0$
0%
0(
#730000
b10 :
b10 ;
b1 7
1(
#740000
0(
#750000
04
03
b1 6
b0 :
b0 ;
1(
#760000
0(
#770000
b100000110010 A
b100000110010 0
b100000110010 E
b1 /
b0 ?
b1 D
b1 8
1(
#780000
0(
#790000
1(
#800000
0(
#810000
1(
#820000
0(
#830000
b10 K
1$
1(
#840000
0(
#850000
b1 :
1(
#860000
0(
#870000
14
b11 :
bz !
bz -
b100 K
0*
1(
#880000
0(
#890000
bz 7
1(
#900000
0(
#910000
bz 6
1(
#920000
0(
#930000
1(
#940000
0(
#950000
b1000 K
0&
1(
#960000
0(
#970000
b10 <
1(
#980000
0(
#990000
b0 !
b0 -
1.
02
b0 <
1(
#1000000
0(
#1010000
b0 7
1(
#1020000
0(
#1030000
b0 6
1(
#1040000
0(
#1050000
1(
#1060000
0(
#1070000
1(
#1080000
0(
#1090000
1(
#1100000
0(
#1110000
b110 K
1%
1&
b0 H
1(
#1120000
0(
#1130000
b1 <
b1 ;
1(
#1140000
0(
#1150000
bz !
bz -
0.
12
13
b11 <
b11 ;
1(
#1160000
0(
#1170000
bz 7
1(
#1180000
0(
#1190000
bz 6
1(
#1200000
0(
#1210000
1(
#1220000
0(
#1230000
b1001000110100 J
b1 I
1(
#1240000
b1 !
b1 -
1*
0$
0%
0(
#1250000
b10 :
b10 ;
b1 7
1(
#1260000
0(
#1270000
04
03
b1 6
b0 :
b0 ;
1(
#1280000
0(
#1290000
1(
#1300000
0(
#1310000
1(
#1320000
0(
#1330000
1(
#1340000
0(
#1350000
b100 K
1$
1(
#1360000
0(
#1370000
b1 :
1(
#1380000
0(
#1390000
14
b11 :
1(
#1400000
0(
#1410000
1(
#1420000
0(
#1430000
b1001000110100 !
b1001000110100 -
b110 K
0'
b1001000110100 +
1(
#1440000
0(
#1450000
b10 >
b1001000110100 7
1(
#1460000
0(
#1470000
01
b1001000110100 6
b0 >
1(
#1480000
0(
#1490000
b1001000110100 C
0=
1(
#1500000
0(
#1510000
1(
#1520000
0(
#1530000
1(
#1540000
0(
#1550000
b100 K
1'
1(
#1560000
0(
#1570000
b1 >
1(
#1580000
0(
#1590000
11
b11 >
1(
#1600000
0(
#1610000
b1001000110100 ?
b1001000110100 @
1=
1(
#1620000
0(
#1630000
bz !
bz -
b110 K
1%
0*
1(
#1640000
0(
#1650000
b1 ;
bz 7
1(
#1660000
0(
#1670000
13
bz 6
b11 ;
1(
#1680000
0(
#1690000
1(
#1700000
0(
#1710000
1(
#1720000
0(
#1730000
1(
#1740000
0(
#1750000
b1001000110100 G
1(
#1760000
b1 !
b1 -
1*
b1 +
0$
0%
0(
#1770000
b10 :
b10 ;
b1 7
1(
#1780000
0(
#1790000
04
03
b1 6
b0 :
b0 ;
1(
#1800000
0(
#1810000
1(
#1820000
0(
#1830000
1(
#1840000
0(
#1850000
1(
#1860000
0(
#1870000
b10 K
1$
1(
#1880000
0(
#1890000
b1 :
1(
#1900000
0(
#1910000
14
b11 :
bz !
bz -
b100 K
0*
1(
#1920000
0(
#1930000
bz 7
1(
#1940000
0(
#1950000
bz 6
1(
#1960000
0(
#1970000
1(
#1980000
0(
#1990000
b1000 K
0&
1(
#2000000
0(
#2010000
b10 <
1(
#2020000
0(
#2030000
b1001000110100 !
b1001000110100 -
1.
02
b0 <
1(
#2040000
0(
#2050000
b1001000110100 7
1(
#2060000
0(
#2070000
b1001000110100 6
1(
#2080000
0(
#2090000
1(
#2100000
0(
#2110000
1(
#2120000
0(
#2130000
1(
#2140000
0(
#2150000
b110 K
1%
1&
b1001000110100 H
1(
#2160000
0(
#2170000
b1 <
b1 ;
1(
#2180000
0(
#2190000
bz !
bz -
0.
12
13
b11 <
b11 ;
1(
#2200000
0(
#2210000
bz 7
1(
#2220000
0(
#2230000
bz 6
1(
#2240000
0(
#2250000
1(
#2260000
0(
#2270000
b101010 J
b10 I
1(
#2280000
b10 !
b10 -
1*
b10 +
0$
0%
0(
#2290000
b10 :
b10 ;
b10 7
1(
#2300000
0(
#2310000
04
03
b10 6
b0 :
b0 ;
1(
#2320000
0(
#2330000
b100001100100 A
b100001100100 0
b100001100100 E
b10 /
b0 ?
b10 D
b10 8
1(
#2340000
0(
#2350000
1(
#2360000
0(
#2370000
1(
#2380000
0(
#2390000
b100 K
1$
1(
#2400000
0(
#2410000
b1 :
1(
#2420000
0(
#2430000
14
b11 :
1(
#2440000
0(
#2450000
1(
#2460000
0(
#2470000
b101010 !
b101010 -
b110 K
0'
b101010 +
1(
#2480000
0(
#2490000
b10 >
b101010 7
1(
#2500000
0(
#2510000
01
b101010 6
b0 >
1(
#2520000
0(
#2530000
b101010 C
0=
1(
#2540000
0(
#2550000
1(
#2560000
0(
#2570000
1(
#2580000
0(
#2590000
b100 K
1'
1(
#2600000
0(
#2610000
b1 >
1(
#2620000
0(
#2630000
11
b11 >
1(
#2640000
0(
#2650000
b101010 ?
b101010 #
b101010 9
1=
1(
#2660000
0(
#2670000
bz !
bz -
b110 K
1%
0*
1(
#2680000
0(
#2690000
b1 ;
bz 7
1(
#2700000
0(
#2710000
13
bz 6
b11 ;
1(
#2720000
0(
#2730000
1(
#2740000
0(
#2750000
1(
#2760000
0(
#2770000
1(
#2780000
0(
#2790000
b101010 G
b10 F
1(
#2800000
b10 !
b10 -
1*
b10 +
0$
0%
0(
#2810000
b10 :
b10 ;
b10 7
1(
#2820000
0(
#2830000
04
03
b10 6
b0 :
b0 ;
1(
#2840000
0(
#2850000
1(
#2860000
0(
#2870000
1(
#2880000
0(
#2890000
1(
#2900000
0(
#2910000
b10 K
1$
1(
#2920000
0(
#2930000
b1 :
1(
#2940000
0(
#2950000
14
b11 :
bz !
bz -
b100 K
0*
1(
#2960000
0(
#2970000
bz 7
1(
#2980000
0(
#2990000
bz 6
1(
#3000000
0(
#3010000
1(
#3020000
0(
#3030000
b1000 K
0&
1(
#3040000
0(
#3050000
b10 <
1(
#3060000
0(
#3070000
b101010 !
b101010 -
1.
02
b0 <
1(
#3080000
0(
#3090000
b101010 7
1(
#3100000
0(
#3110000
b101010 6
1(
#3120000
0(
#3130000
1(
#3140000
0(
#3150000
1(
#3160000
0(
#3170000
1(
#3180000
0(
#3190000
b110 K
1%
1&
b101010 H
1(
#3200000
0(
#3210000
b1 <
b1 ;
1(
#3220000
0(
#3230000
bz !
bz -
0.
12
13
b11 <
b11 ;
1(
#3240000
0(
#3250000
bz 7
1(
#3260000
0(
#3270000
bz 6
1(
